coveo_testing_extras/__init__.py
coveo_testing_extras/py.typed
coveo_testing_extras/temporary_resource/__init__.py
coveo_testing_extras/temporary_resource/docker_container.py
coveo_testing_extras-3.0.1.dist-info/METADATA
coveo_testing_extras-3.0.1.dist-info/WHEEL
coveo_testing_extras-3.0.1.dist-info/RECORD
