Metadata-Version: 2.1
Name: coveo-testing-extras
Version: 3.0.1
Summary: Dependency-hungry testing helpers
Home-page: https://github.com/coveooss/coveo-python-oss/tree/main/coveo-testing-extras
License: Apache-2.0
Author: Jonathan Piché
Author-email: tools@coveo.com
Requires-Python: >=3.9,<4
Classifier: License :: OSI Approved :: Apache Software License
Classifier: Programming Language :: Python :: 3
Classifier: Programming Language :: Python :: 3.9
Classifier: Programming Language :: Python :: 3.10
Classifier: Programming Language :: Python :: 3.11
Requires-Dist: coveo-functools
Requires-Dist: coveo-settings
Requires-Dist: coveo-systools
Requires-Dist: coveo-testing
Requires-Dist: docker
Project-URL: Repository, https://github.com/coveooss/coveo-python-oss/tree/main/coveo-testing-extras
